{
    "basic_info": {
      "description_header": "Hola",
      "description": " Soy Araceli. Soy un solucionador de problemas altamente motivado con fuertes habilidades anal铆ticas y de resoluci贸n de problemas con una licenciatura en Bioqu铆mica y Qu铆mica. Tengo m谩s de 4 a帽os de experiencia trabajando en el campo de la ciencia. Di el salto al desarrollo de software cuando vi la necesidad de mejorar la forma de comunicaci贸n, el seguimiento del progreso y la asignaci贸n de trabajos con tecnolog铆a en lugar de l谩piz y papel en la empresa en la que sol铆a trabajar. Luego entre en la Programa de desarrollo web y m贸vil de Epicodus en mayo de 2021 y desde entonces he estado en mi camino para convertirme en un desarrollador de software de pila completa.",
      "section_name": {
        "about": "Acerca de m铆",
        "projects": "Proyectos",
        "skills": "Habilidades",
        "experience": "Cronolog铆a"
      }
    },
    "projects": [
      {
        "title": "Galactic Calculator",
        "startDate": "2021",
        "description": "Una aplicaci贸n web que determina la edad de un usuario en funci贸n de los a帽os solares de un planeta.",
        "images": [
          "/images/portfolio/galactic-calculator/p1.png",
          "/images/portfolio/galactic-calculator/p2.png"
        ],
        "url": "https://aracelivaldovinos.github.io/js-galactic-calc/",
        "technologies": [
          {
            "class": "devicon-javascript-plain",
            "name": "JavaScript"
          },
          {
            "class": "devicon-jquery-plain",
            "name": "jQuery"
          },
          {
            "class": "devicon-html5-plain",
            "name": "HTML5"
          },
          {
            "class": "devicon-css3-plain",
            "name": "CSS3"
          },
          {
            "class": "devicon-bootstrap-plain",
            "name": "Bootstrap"
          }
        ]
      },
      {
        "title": "Currency Converter",
        "startDate": "2021",
        "description": "Una aplicaci贸n que permite a los usuarios convertir d贸lares americano a otra moneda usando ExchangeRate-API.",
        "images": [
          "/images/portfolio/currency-converter/p1.png",
          "/images/portfolio/currency-converter/p2.png"
        ],
        "url": "https://aracelivaldovinos.github.io/js-currency-converter/",
        "technologies": [
          {
            "class": "devicon-javascript-plain",
            "name": "JavaScript"
          },
          {
            "class": "devicon-jquery-plain",
            "name": "jQuery"
          },
          {
            "class": "devicon-html5-plain",
            "name": "HTML5"
          },
          {
            "class": "devicon-css3-plain",
            "name": "CSS3"
          },
          {
            "class": "devicon-bootstrap-plain",
            "name": "Bootstrap"
          }
        ]
      },
      {
        "title": "Volunteer Tracker",
        "startDate": "2021",
        "description": "Volunteer Tracker es una aplicaci贸n que realiza un seguimiento de los proyectos y los voluntarios. Cada voluntario pertenecer谩 a un solo proyecto (un proyecto, muchos voluntarios). La aplicaci贸n est谩 construida sobre Ruby y practica Test Driven Development.",
        "images": [
          "/images/portfolio/volunteer-tracker/p1.png",
          "/images/portfolio/volunteer-tracker/p2.png",
          "/images/portfolio/volunteer-tracker/p3.png",
          "/images/portfolio/volunteer-tracker/p4.png",
          "/images/portfolio/volunteer-tracker/p5.png"
        ],
        "url": "https://github.com/aracelivaldovinos/ruby-volunteer-tracker",
        "technologies": [
          {
            "class": "devicon-ruby-plain",
            "name": "Ruby"
          },
          {
            "class": "devicon-postgresql-plain",
            "name": "postgreSQL"
          },
          {
            "class": "devicon-html5-plain",
            "name": "HTML5"
          },
          {
            "class": "devicon-css3-plain",
            "name": "CSS3"
          },
          {
            "class": "devicon-bootstrap-plain",
            "name": "Bootstrap"
          }
        ]
      },
      {
        "title": "Mario's Coffeeshop",
        "startDate": "2021",
        "description": "El sitio web Marios Coffeeshop permite a los clientes ver y calificar el caf茅 de Mario. Este proyecto practica la implementaci贸n de la funcionalidad CRUD completa, la autenticaci贸n y autorizaci贸n de usuarios con Ruby on Rails. Los usuarios pueden crear y leer rese帽as, pero solo pueden editar y eliminar sus propias rese帽as. El administrador puede crear, leer, editar y eliminar caf茅s. Para acceder al lado de administraci贸n de la aplicaci贸n, use las siguientes credenciales: correo electr贸nico: email@testing.com contrase帽a: contrase帽a.",
        "images": [
          "/images/portfolio/coffeeshop/p1.png",
          "/images/portfolio/coffeeshop/p2.png",
          "/images/portfolio/coffeeshop/p3.png",
          "/images/portfolio/coffeeshop/p4.png",
          "/images/portfolio/coffeeshop/p5.png",
          "/images/portfolio/coffeeshop/p6.png"
        ],
        "url": "https://github.com/aracelivaldovinos/rails-marios-coffeeshop",
        "technologies": [
          {
            "class": "devicon-ruby-plain",
            "name": "Ruby"
          },
          {
            "class": "devicon-rails-plain",
            "name": "Rails"
          },
          {
            "class": "devicon-postgresql-plain",
            "name": "postgreSQL"
          },
          {
            "class": "devicon-html5-plain",
            "name": "HTML5"
          },
          {
            "class": "devicon-css3-plain",
            "name": "CSS3"
          },
          {
            "class": "devicon-bootstrap-plain",
            "name": "Bootstrap"
          }
        ]
      },
      {
        "title": "Brewery Taproom",
        "startDate": "2021",
        "description": "Brewery taproom es una aplicaci贸n de taberna integrada en React donde una tienda de cervecer铆a puede rastrear las pintas restantes en un barril. La aplicaci贸n tiene una funcionalidad CRUD completa, el administrador puede crear, leer, actualizar y eliminar un elemento. Para acceder al lado de administraci贸n de la aplicaci贸n, use las siguientes credenciales: Correo electr贸nico: admin@admintest.com Contrase帽a: admin123.",
        "images": [
          "/images/portfolio/taproom/p1.png",
          "/images/portfolio/taproom/p2.png",
          "/images/portfolio/taproom/p3.png",
          "/images/portfolio/taproom/p4.png",
          "/images/portfolio/taproom/p5.png"
        ],
        "url": "https://brewery-taproom.firebaseapp.com/",
        "technologies": [
          {
            "class": "devicon-react-original",
            "name": "React"
          },
          {
            "class": "devicon-firebase-plain",
            "name": "Firebase"
          },
          {
            "class": "devicon-html5-plain",
            "name": "HTML5"
          },
          {
            "class": "devicon-css3-plain",
            "name": "CSS3"
          },
          {
            "class": "devicon-bootstrap-plain",
            "name": "Bootstrap"
          }
        ]
      },
      {
        "title": "Tarot Tonight",
        "startDate": "2021",
        "description": "Tarot Tonight es una aplicaci贸n de adivinaci贸n creada en grupo que reparte tres cartas al usuario. La aplicacion hace llamadas a varias API para recuperar informaci贸n relacionada con las tarjetas.",
        "images": [
          "/images/portfolio/tarot/p1.png"  
        ],
        "url": "https://github.com/aracelivaldovinos/js-tarot-tonight",
        "technologies": [
          {
            "class": "devicon-javascript-plain",
            "name": "JavaScript"
          },
          {
            "class": "devicon-jquery-plain",
            "name": "jQuery"
          },
          {
            "class": "devicon-html5-plain",
            "name": "HTML5"
          },
          {
            "class": "devicon-css3-plain",
            "name": "CSS3"
          },
          {
            "class": "devicon-bootstrap-plain",
            "name": "Bootstrap"
          }
        ]
      }
    ],
    "experience": [
      {
        "company": "Epicodus",
        "title": "Estudiante",
        "years": "05.2021 - present",
        "mainTech": [
          "Programa de Desarrollo Web y M贸vil"
        ],
        "technologies": [
          "JavaScript",
          "jQuery",
          "Ruby",
          "React",
          "Rails",
          "Bootstrap",
          "SQL & NoSQL Databases",
          "REST API",
          "Jest",
          "TDD",
          "GitHub Workflow"
        ]
      },
      {
        "company": "Dept. of Public Safety, Crime Lab",
        "title": "Cient铆fica forense",
        "years": "09.2019 - 05.2021",
        "mainTech": [
        ],
        "technologies": [
        ]
      },
      {
        "company": "University of Texas at San Antonio, Dept. of Chemistry",
        "title": "Investigador asociado",
        "years": "12.2016 - 01.2019",
        "mainTech": [
        ],
        "technologies": [
        ]
      }
    ]
  }